odoo/addons/pos_product_packaging_container_deposit/README.rst
odoo/addons/pos_product_packaging_container_deposit/__init__.py
odoo/addons/pos_product_packaging_container_deposit/__manifest__.py
odoo/addons/pos_product_packaging_container_deposit/i18n/es.po
odoo/addons/pos_product_packaging_container_deposit/i18n/it.po
odoo/addons/pos_product_packaging_container_deposit/i18n/pos_product_packaging_container_deposit.pot
odoo/addons/pos_product_packaging_container_deposit/models/__init__.py
odoo/addons/pos_product_packaging_container_deposit/models/pos_order_line.py
odoo/addons/pos_product_packaging_container_deposit/models/pos_session.py
odoo/addons/pos_product_packaging_container_deposit/models/product_packaging.py
odoo/addons/pos_product_packaging_container_deposit/readme/CONTRIBUTORS.rst
odoo/addons/pos_product_packaging_container_deposit/readme/CREDITS.rst
odoo/addons/pos_product_packaging_container_deposit/readme/DESCRIPTION.rst
odoo/addons/pos_product_packaging_container_deposit/readme/USAGE.rst
odoo/addons/pos_product_packaging_container_deposit/static/description/icon.png
odoo/addons/pos_product_packaging_container_deposit/static/description/index.html
odoo/addons/pos_product_packaging_container_deposit/static/src/js/ProductScreen.esm.js
odoo/addons/pos_product_packaging_container_deposit/static/src/js/models.esm.js
odoo/addons/pos_product_packaging_container_deposit/tests/__init__.py
odoo/addons/pos_product_packaging_container_deposit/tests/test_deposit.py
odoo/addons/pos_product_packaging_container_deposit/tests/tours/TestDepostit.tour.js
odoo_addon_pos_product_packaging_container_deposit-16.0.1.1.0.dist-info/METADATA
odoo_addon_pos_product_packaging_container_deposit-16.0.1.1.0.dist-info/WHEEL
odoo_addon_pos_product_packaging_container_deposit-16.0.1.1.0.dist-info/top_level.txt
odoo_addon_pos_product_packaging_container_deposit-16.0.1.1.0.dist-info/RECORD
